luca_frames/__init__.py
luca_frames/csv_helper.py
luca_frames/logger_helper.py
luca_frames/path_helper.py
luca_frames/time_helper.py
luca_frames-0.0.1.dist-info/METADATA
luca_frames-0.0.1.dist-info/WHEEL
luca_frames-0.0.1.dist-info/licenses/LICENSE
luca_frames-0.0.1.dist-info/RECORD
