Metadata-Version: 2.3
Name: luca_frames
Version: 0.0.1
Summary: A small package with helper functions
Project-URL: Homepage, https://github.com/Zoneee/py_helpers
Project-URL: Issues, https://github.com/Zoneee/py_helpers/issues
Author-email: alphonse luca <alphonseluca@163.com>
License: MIT License
License-File: LICENSE
Classifier: License :: OSI Approved :: MIT License
Classifier: Operating System :: OS Independent
Classifier: Programming Language :: Python :: 3
Requires-Python: >=3.6
